angelq_client/__init__.py
angelq_client/client.py
angelq_client-1.0.1.dist-info/licenses/LICENSE
angelq_client-1.0.1.dist-info/METADATA
angelq_client-1.0.1.dist-info/WHEEL
angelq_client-1.0.1.dist-info/top_level.txt
angelq_client-1.0.1.dist-info/RECORD
