Metadata-Version: 2.4
Name: angelq-client
Version: 1.0.1
Summary: Python client for AngelQ APIs
Author-email: Andreas Stratakis <andrew.stratakis@gmail.com>
License: MIT
Project-URL: Homepage, https://github.com/angelquantum/angelq-client
Project-URL: Issues, https://github.com/angelquantum/angelq-client/issues
Classifier: Development Status :: 4 - Beta
Classifier: Programming Language :: Python :: 3
Classifier: License :: OSI Approved :: MIT License
Classifier: Operating System :: OS Independent
Requires-Python: >=3.9
License-File: LICENSE
Requires-Dist: requests>=2.32.5
Dynamic: license-file
